target_snowflake/__init__.py
target_snowflake/connection.py
target_snowflake/exceptions.py
target_snowflake/snowflake.py
target_snowflake/sql.py
target_snowflake-0.2.4.dist-info/LICENSE
target_snowflake-0.2.4.dist-info/METADATA
target_snowflake-0.2.4.dist-info/WHEEL
target_snowflake-0.2.4.dist-info/entry_points.txt
target_snowflake-0.2.4.dist-info/top_level.txt
target_snowflake-0.2.4.dist-info/RECORD
