Metadata-Version: 2.1
Name: target-snowflake
Version: 0.2.4
Summary: Singer.io target for loading data into Snowflake
Home-page: https://github.com/datamill-co/target-snowflake
Author: datamill
License: UNKNOWN
Platform: UNKNOWN
Classifier: Programming Language :: Python :: 3 :: Only
Requires-Dist: singer-python (==5.9.0)
Requires-Dist: singer-target-postgres (==0.2.4)
Requires-Dist: target-redshift (==0.2.4)
Requires-Dist: botocore (<1.13.0,>=1.12.253)
Requires-Dist: snowflake-connector-python (==2.2.5)
Provides-Extra: tests
Requires-Dist: chance (==0.110) ; extra == 'tests'
Requires-Dist: Faker (==4.0.3) ; extra == 'tests'
Requires-Dist: pytest (==5.4.1) ; extra == 'tests'
